Metadata-Version: 2.4
Name: ScreenTranslator
Version: 0.1.0
Requires-Python: >=3.9
License-File: LICENSE
Requires-Dist: pytest==8.3.3
Requires-Dist: torch>=2.4.1
Requires-Dist: PyYAML~=6.0.2
Requires-Dist: pillow~=11.0.0
Requires-Dist: torchvision~=0.20.1
Requires-Dist: matplotlib~=3.9.4
Requires-Dist: numpy~=1.26.4
Requires-Dist: ultralytics~=8.3.50
Requires-Dist: opencv-python~=4.10.0.84
Requires-Dist: pandas~=2.2.3
Requires-Dist: seaborn~=0.13.2
Requires-Dist: scipy~=1.13.1
Requires-Dist: requests~=2.32.3
Requires-Dist: tqdm~=4.67.1
Requires-Dist: psutil~=6.1.0
Requires-Dist: thop~=0.1.1.post2209072238
Requires-Dist: ultralytics-thop~=2.0.13
Requires-Dist: flask
Requires-Dist: flasgger
Requires-Dist: flask_limiter
Requires-Dist: deep_translator
Requires-Dist: pillow_heif
Requires-Dist: gitpython>=3.1.30
Requires-Dist: matplotlib>=3.3
Requires-Dist: numpy>=1.23.5
Requires-Dist: opencv-python>=4.1.1
Requires-Dist: pillow>=10.3.0
Requires-Dist: psutil
Requires-Dist: PyYAML>=5.3.1
Requires-Dist: requests>=2.32.2
Requires-Dist: scipy>=1.4.1
Requires-Dist: thop>=0.1.1
Requires-Dist: torch>=1.8.0
Requires-Dist: torchvision>=0.9.0
Requires-Dist: tqdm>=4.66.3
Requires-Dist: ultralytics>=8.2.34
Requires-Dist: pandas>=1.1.4
Requires-Dist: seaborn>=0.11.0
Requires-Dist: setuptools>=70.0.0
Requires-Dist: vidgear~=0.3.3
Requires-Dist: future~=0.18.2
Requires-Dist: flask~=3.1.0
Requires-Dist: werkzeug~=3.1.3
Dynamic: license-file
Dynamic: requires-dist
Dynamic: requires-python
